README.rst
setup.py
src/hecate/__init__.py
src/hecate/hecate.py
src/hecate/runner.py
src/hecate/tmux.py
src/hecate/version.py
src/hecate.egg-info/PKG-INFO
src/hecate.egg-info/SOURCES.txt
src/hecate.egg-info/dependency_links.txt
src/hecate.egg-info/not-zip-safe
src/hecate.egg-info/pbr.json
src/hecate.egg-info/top_level.txt