Metadata-Version: 1.0
Name: hecate
Version: 0.1.0
Summary: A selenium style testing library for console applications
Home-page: https://github.com/DRMacIver/hecate
Author: David R. MacIver
Author-email: david@drmaciver.com
License: MPL v2
Platform: UNKNOWN
